[
  {
    "_id": "613680ecd642c471bb454c22",
    "index": 0,
    "guid": "71976b55-1683-4f8c-bcc8-c26dabd7067e",
    "isActive": true,
    "balance": "$2,776.13",
    "age": 28,
    "eyeColor": "brown",
    "name": "Tucker Hoffman",
    "gender": "male",
    "company": "STELAECOR",
    "email": "tuckerhoffman@stelaecor.com",
    "phone": "+1 (945) 564-3359",
    "address": "329 Duryea Place, Downsville, Wyoming, 654",
    "about": "Id aliqua voluptate consequat tempor velit veniam nisi et. Incididunt consectetur occaecat ullamco Lorem laborum minim nostrud voluptate sint ea laboris incididunt reprehenderit. Ex anim irure aliquip laboris ullamco ullamco ut. Duis eu ut amet magna quis et Lorem adipisicing voluptate ea.\r\n",
    "registered": "2017-04-09T02:17:36 +03:00",
    "latitude": -9.129461,
    "longitude": 88.095358
  }
]